{
  "db_name": "PostgreSQL",
  "query": "DELETE FROM user_skills\n        WHERE id IN (\n            SELECT ups.user_skill_id FROM user_plugin_skills ups\n            WHERE ups.user_plugin_id = $1\n            AND NOT EXISTS (\n                SELECT 1 FROM user_plugin_skills ups2\n                WHERE ups2.user_skill_id = ups.user_skill_id\n                AND ups2.user_plugin_id != $1\n            )\n        ) AND updated_at <= created_at",
  "describe": {
    "columns": [],
    "parameters": {
      "Left": [
        "Text"
      ]
    },
    "nullable": []
  },
  "hash": "db053aa40a3c603942d351765f2ed05ed7e91c5f04a7b02967fb00a3ffcb488c"
}
