{
  "db_name": "PostgreSQL",
  "query": "SELECT\n            EXTRACT(HOUR FROM created_at)::DOUBLE PRECISION AS hour,\n            COUNT(*) FILTER (WHERE event_type IN ('PostToolUse', 'UserPromptSubmit')) AS actions,\n            COUNT(*) FILTER (WHERE event_type = 'PostToolUseFailure') AS errors,\n            COUNT(DISTINCT tool_name) FILTER (WHERE event_type = 'PostToolUse') AS unique_tools\n          FROM plugin_usage_events\n          WHERE user_id = $1\n            AND created_at::date = CURRENT_DATE\n          GROUP BY 1",
  "describe": {
    "columns": [
      {
        "ordinal": 0,
        "name": "hour",
        "type_info": "Float8"
      },
      {
        "ordinal": 1,
        "name": "actions",
        "type_info": "Int8"
      },
      {
        "ordinal": 2,
        "name": "errors",
        "type_info": "Int8"
      },
      {
        "ordinal": 3,
        "name": "unique_tools",
        "type_info": "Int8"
      }
    ],
    "parameters": {
      "Left": [
        "Text"
      ]
    },
    "nullable": [
      null,
      null,
      null,
      null
    ]
  },
  "hash": "b33db19e4c8ad350b5a5b70005ddc32735818ddf7c86ea3c7ebaf0d5fe6fd35a"
}
