{
  "db_name": "PostgreSQL",
  "query": "\n            INSERT INTO user_device_certs (id, user_id, fingerprint, label)\n            VALUES ($1, $2, $3, $4)\n            RETURNING id, user_id, fingerprint, label, enrolled_at, revoked_at\n            ",
  "describe": {
    "columns": [
      {
        "ordinal": 0,
        "name": "id",
        "type_info": "Text",
        "origin": {
          "Table": {
            "table": "user_device_certs",
            "name": "id"
          }
        }
      },
      {
        "ordinal": 1,
        "name": "user_id",
        "type_info": "Text",
        "origin": {
          "Table": {
            "table": "user_device_certs",
            "name": "user_id"
          }
        }
      },
      {
        "ordinal": 2,
        "name": "fingerprint",
        "type_info": "Varchar",
        "origin": {
          "Table": {
            "table": "user_device_certs",
            "name": "fingerprint"
          }
        }
      },
      {
        "ordinal": 3,
        "name": "label",
        "type_info": "Varchar",
        "origin": {
          "Table": {
            "table": "user_device_certs",
            "name": "label"
          }
        }
      },
      {
        "ordinal": 4,
        "name": "enrolled_at",
        "type_info": "Timestamptz",
        "origin": {
          "Table": {
            "table": "user_device_certs",
            "name": "enrolled_at"
          }
        }
      },
      {
        "ordinal": 5,
        "name": "revoked_at",
        "type_info": "Timestamptz",
        "origin": {
          "Table": {
            "table": "user_device_certs",
            "name": "revoked_at"
          }
        }
      }
    ],
    "parameters": {
      "Left": [
        "Text",
        "Text",
        "Varchar",
        "Varchar"
      ]
    },
    "nullable": [
      false,
      false,
      false,
      false,
      false,
      true
    ]
  },
  "hash": "09fdca6e9a36d360ddd6a550eeb8100abdb4a107a369b148e6bb31a9eb8bfc29"
}
