{
  "db_name": "PostgreSQL",
  "query": "SELECT category, SUM(count)::BIGINT AS total\n          FROM (\n            SELECT jsonb_object_keys(category_distribution) AS category,\n                   (category_distribution ->> jsonb_object_keys(category_distribution))::BIGINT AS count\n            FROM daily_summaries\n            WHERE user_id = $1\n              AND summary_date >= CURRENT_DATE - MAKE_INTERVAL(days => $2)\n              AND category_distribution IS NOT NULL\n          ) sub\n          GROUP BY category\n          ORDER BY total DESC",
  "describe": {
    "columns": [
      {
        "ordinal": 0,
        "name": "category",
        "type_info": "Text"
      },
      {
        "ordinal": 1,
        "name": "total",
        "type_info": "Int8"
      }
    ],
    "parameters": {
      "Left": [
        "Text",
        "Int4"
      ]
    },
    "nullable": [
      null,
      null
    ]
  },
  "hash": "3fc6ee7210d9ea78b25c4ddb7208a52ca1e91a835c234e9681ddbfcde1b8b1b8"
}
