{
  "db_name": "PostgreSQL",
  "query": "\n        SELECT endpoint\n        FROM analytics_events\n        WHERE session_id = $1\n          AND event_type = 'page_view'\n        ORDER BY timestamp ASC\n        ",
  "describe": {
    "columns": [
      {
        "ordinal": 0,
        "name": "endpoint",
        "type_info": "Text"
      }
    ],
    "parameters": {
      "Left": [
        "Text"
      ]
    },
    "nullable": [
      true
    ]
  },
  "hash": "da50eeb5b78f408e552a55e78a232bd229bb8e10dbf145a5abc55fabb0fbed19"
}
